TERRA_GA/TXT_Classification_GA.py
TERRA_GA/__init__.py
TERRA_GA_TXT_Classification-0.0.23.dist-info/LICENSE.txt
TERRA_GA_TXT_Classification-0.0.23.dist-info/METADATA
TERRA_GA_TXT_Classification-0.0.23.dist-info/WHEEL
TERRA_GA_TXT_Classification-0.0.23.dist-info/top_level.txt
TERRA_GA_TXT_Classification-0.0.23.dist-info/RECORD
