Metadata-Version: 2.1
Name: TERRA-GA-TXT-Classification
Version: 0.0.23
Summary: GA for best models for texts classification
Author: Svetlana Luneva
Author-email: mibellisvetlana@gmail.com
Classifier: Programming Language :: Python :: 3
Classifier: License :: OSI Approved :: MIT License
Classifier: Operating System :: OS Independent
Requires-Python: >=3.6
License-File: LICENSE.txt
